sneks/engine/__init__.py
sneks/engine/graphics.py
sneks/engine/recorder.py
sneks/engine/registrar.py
sneks/engine/runner.py
sneks/engine/scoring.py
sneks/engine/util.py
sneks/engine/world.py
sneks/engine/config/__init__.py
sneks/engine/config/base.py
sneks/engine/config/color.py
sneks/engine/config/entity.py
sneks/engine/config/graphics.py
sneks/engine/config/snek.py
sneks/engine/config/world.py
sneks/engine/core/__init__.py
sneks/engine/core/action.py
sneks/engine/core/bearing.py
sneks/engine/core/cell.py
sneks/engine/core/direction.py
sneks/engine/core/snek.py
sneks/engine/entity/__init__.py
sneks/engine/entity/asteroid.py
sneks/engine/entity/base.py
sneks/engine/entity/dynamic.py
sneks/engine/entity/food.py
sneks/engine/entity/snek.py
sneks/engine/entity/static.py
sneks/engine/manager/__init__.py
sneks/engine/manager/bearing.py
sneks/engine/manager/cell.py
sneks/engine/validator/__init__.py
sneks/engine/validator/main.py
sneks/engine/validator/test_existance.py
sneks/engine/validator/test_functionality.py
sneks/games/__init__.py
sneks/games/classic/__init__.py
sneks/games/classic/config.py
sneks/games/classic/world.py
sneks/games/space/__init__.py
sneks/games/space/config.py
sneks/games/space/world.py
sneks/games/toroidal/__init__.py
sneks/games/toroidal/config.py
sneks/games/toroidal/world.py
sneks_engine-1.0.5.dist-info/METADATA
sneks_engine-1.0.5.dist-info/WHEEL
sneks_engine-1.0.5.dist-info/licenses/LICENSE
sneks_engine-1.0.5.dist-info/RECORD
