Metadata-Version: 2.4
Name: sneks-engine
Version: 1.0.5
Summary: Sneks engine
Author-email: Nathaniel Schaaf <nathaniel.schaaf@gmail.com>
License-Expression: Apache-2.0
License-File: LICENSE
Classifier: License :: OSI Approved :: Apache Software License
Classifier: Programming Language :: Python :: 3
Classifier: Programming Language :: Python :: 3.10
Classifier: Programming Language :: Python :: 3.11
Classifier: Programming Language :: Python :: 3.12
Classifier: Programming Language :: Python :: 3.13
Classifier: Programming Language :: Python :: 3.14
Classifier: Typing :: Typed
Requires-Python: >=3.10
Requires-Dist: pygame>=2.6.1
Requires-Dist: pytest
Provides-Extra: dev
Requires-Dist: pyright; extra == 'dev'
Requires-Dist: ruff; extra == 'dev'
Provides-Extra: record
Requires-Dist: imageio-ffmpeg; extra == 'record'
